<annotation>
	<folder>images</folder>
	<filename>Buffy_449.jpg</filename>
	<path>C:\Users\jiwon_2\Downloads\training_data\images\Buffy_449.jpg</path>
	<source>
		<database>Unknown</database>
	</source>
	<size>
		<width>633</width>
		<height>702</height>
		<depth>3</depth>
	</size>
	<segmented>0</segmented>
	<object>
		<name>hand</name>
		<pose>Unspecified</pose>
		<truncated>0</truncated>
		<difficult>0</difficult>
		<bndbox>
			<xmin>448</xmin>
			<ymin>497</ymin>
			<xmax>486</xmax>
			<ymax>542</ymax>
		</bndbox>
	</object>
	<object>
		<name>hand</name>
		<pose>Unspecified</pose>
		<truncated>0</truncated>
		<difficult>0</difficult>
		<bndbox>
			<xmin>230</xmin>
			<ymin>408</ymin>
			<xmax>277</xmax>
			<ymax>451</ymax>
		</bndbox>
	</object>
	<object>
		<name>hand</name>
		<pose>Unspecified</pose>
		<truncated>0</truncated>
		<difficult>0</difficult>
		<bndbox>
			<xmin>353</xmin>
			<ymin>419</ymin>
			<xmax>390</xmax>
			<ymax>484</ymax>
		</bndbox>
	</object>
</annotation>
