<annotation>
	<folder>Buffy_7</folder>
	<filename>Inria_96.jpg</filename>
	<path>C:\Users\jiwon_2\Desktop\Buffy_7\Inria_96.jpg</path>
	<source>
		<database>Unknown</database>
	</source>
	<size>
		<width>1239</width>
		<height>976</height>
		<depth>3</depth>
	</size>
	<segmented>0</segmented>
	<object>
		<name>hand</name>
		<pose>Unspecified</pose>
		<truncated>0</truncated>
		<difficult>0</difficult>
		<bndbox>
			<xmin>642</xmin>
			<ymin>315</ymin>
			<xmax>726</xmax>
			<ymax>398</ymax>
		</bndbox>
	</object>
	<object>
		<name>hand</name>
		<pose>Unspecified</pose>
		<truncated>0</truncated>
		<difficult>0</difficult>
		<bndbox>
			<xmin>979</xmin>
			<ymin>317</ymin>
			<xmax>1042</xmax>
			<ymax>367</ymax>
		</bndbox>
	</object>
	<object>
		<name>hand</name>
		<pose>Unspecified</pose>
		<truncated>0</truncated>
		<difficult>0</difficult>
		<bndbox>
			<xmin>1113</xmin>
			<ymin>332</ymin>
			<xmax>1166</xmax>
			<ymax>374</ymax>
		</bndbox>
	</object>
	<object>
		<name>hand</name>
		<pose>Unspecified</pose>
		<truncated>0</truncated>
		<difficult>0</difficult>
		<bndbox>
			<xmin>805</xmin>
			<ymin>280</ymin>
			<xmax>866</xmax>
			<ymax>324</ymax>
		</bndbox>
	</object>
</annotation>
